<stg><name>conv_2d_cl<array<ap_fixed,4u>,array<ap_fixed<16,6,5,3,0>,8u>,config5></name>


<trans_list>

<trans id="38" from="1" to="2">
<condition id="-1">
<or_exp><and_exp></and_exp></or_exp>
</condition>
</trans>

<trans id="46" from="2" to="5">
<condition id="-1">
<or_exp><and_exp><literal name="icmp_ln79" val="1"/>
</and_exp></or_exp>
</condition>
</trans>

<trans id="47" from="2" to="3">
<condition id="-1">
<or_exp><and_exp><literal name="icmp_ln79" val="0"/>
</and_exp></or_exp>
</condition>
</trans>

<trans id="44" from="3" to="4">
<condition id="-1">
<or_exp><and_exp></and_exp></or_exp>
</condition>
</trans>

<trans id="45" from="4" to="2">
<condition id="-1">
<or_exp><and_exp></and_exp></or_exp>
</condition>
</trans>
</trans_list>



<state_list>

<state id="1" st_id="1">

<operation id="6" st_id="1" stage="1" lat="1">
<core>NULL</core>
<MemPortIdVec></MemPortIdVec>
<condition id="-1">
<or_exp><and_exp></and_exp></or_exp>
</condition>

<Node id="52" bw="0" op_0_bw="0" op_1_bw="16" op_2_bw="0" op_3_bw="32" op_4_bw="32" op_5_bw="0" op_6_bw="32" op_7_bw="32" op_8_bw="0" op_9_bw="0" op_10_bw="0" op_11_bw="32" op_12_bw="32" op_13_bw="32" op_14_bw="32" op_15_bw="0" op_16_bw="0">
<![CDATA[
codeRepl:0  call void (...)* @_ssdm_op_SpecInterface(i16* %res_V_data_7_V, [8 x i8]* @ap_fifo_str, i32 0, i32 0, [1 x i8]* @p_str474, i32 0, i32 0, [1 x i8]* @p_str475, [1 x i8]* @p_str476, [1 x i8]* @p_str477, i32 2, i32 2, i32 16, i32 16, [1 x i8]* @p_str478, [1 x i8]* @p_str479)

]]></Node>
<StgValue><ssdm name="specinterface_ln0"/></StgValue>
</operation>

<operation id="7" st_id="1" stage="1" lat="1">
<core>NULL</core>
<MemPortIdVec></MemPortIdVec>
<condition id="-1">
<or_exp><and_exp></and_exp></or_exp>
</condition>

<Node id="53" bw="0" op_0_bw="0" op_1_bw="16" op_2_bw="0" op_3_bw="32" op_4_bw="32" op_5_bw="0" op_6_bw="32" op_7_bw="32" op_8_bw="0" op_9_bw="0" op_10_bw="0" op_11_bw="32" op_12_bw="32" op_13_bw="32" op_14_bw="32" op_15_bw="0" op_16_bw="0">
<![CDATA[
codeRepl:1  call void (...)* @_ssdm_op_SpecInterface(i16* %res_V_data_6_V, [8 x i8]* @ap_fifo_str, i32 0, i32 0, [1 x i8]* @p_str467, i32 0, i32 0, [1 x i8]* @p_str468, [1 x i8]* @p_str469, [1 x i8]* @p_str470, i32 2, i32 2, i32 16, i32 16, [1 x i8]* @p_str471, [1 x i8]* @p_str472)

]]></Node>
<StgValue><ssdm name="specinterface_ln0"/></StgValue>
</operation>

<operation id="8" st_id="1" stage="1" lat="1">
<core>NULL</core>
<MemPortIdVec></MemPortIdVec>
<condition id="-1">
<or_exp><and_exp></and_exp></or_exp>
</condition>

<Node id="54" bw="0" op_0_bw="0" op_1_bw="16" op_2_bw="0" op_3_bw="32" op_4_bw="32" op_5_bw="0" op_6_bw="32" op_7_bw="32" op_8_bw="0" op_9_bw="0" op_10_bw="0" op_11_bw="32" op_12_bw="32" op_13_bw="32" op_14_bw="32" op_15_bw="0" op_16_bw="0">
<![CDATA[
codeRepl:2  call void (...)* @_ssdm_op_SpecInterface(i16* %res_V_data_5_V, [8 x i8]* @ap_fifo_str, i32 0, i32 0, [1 x i8]* @p_str460, i32 0, i32 0, [1 x i8]* @p_str461, [1 x i8]* @p_str462, [1 x i8]* @p_str463, i32 2, i32 2, i32 16, i32 16, [1 x i8]* @p_str464, [1 x i8]* @p_str465)

]]></Node>
<StgValue><ssdm name="specinterface_ln0"/></StgValue>
</operation>

<operation id="9" st_id="1" stage="1" lat="1">
<core>NULL</core>
<MemPortIdVec></MemPortIdVec>
<condition id="-1">
<or_exp><and_exp></and_exp></or_exp>
</condition>

<Node id="55" bw="0" op_0_bw="0" op_1_bw="16" op_2_bw="0" op_3_bw="32" op_4_bw="32" op_5_bw="0" op_6_bw="32" op_7_bw="32" op_8_bw="0" op_9_bw="0" op_10_bw="0" op_11_bw="32" op_12_bw="32" op_13_bw="32" op_14_bw="32" op_15_bw="0" op_16_bw="0">
<![CDATA[
codeRepl:3  call void (...)* @_ssdm_op_SpecInterface(i16* %res_V_data_4_V, [8 x i8]* @ap_fifo_str, i32 0, i32 0, [1 x i8]* @p_str453, i32 0, i32 0, [1 x i8]* @p_str454, [1 x i8]* @p_str455, [1 x i8]* @p_str456, i32 2, i32 2, i32 16, i32 16, [1 x i8]* @p_str457, [1 x i8]* @p_str458)

]]></Node>
<StgValue><ssdm name="specinterface_ln0"/></StgValue>
</operation>

<operation id="10" st_id="1" stage="1" lat="1">
<core>NULL</core>
<MemPortIdVec></MemPortIdVec>
<condition id="-1">
<or_exp><and_exp></and_exp></or_exp>
</condition>

<Node id="56" bw="0" op_0_bw="0" op_1_bw="16" op_2_bw="0" op_3_bw="32" op_4_bw="32" op_5_bw="0" op_6_bw="32" op_7_bw="32" op_8_bw="0" op_9_bw="0" op_10_bw="0" op_11_bw="32" op_12_bw="32" op_13_bw="32" op_14_bw="32" op_15_bw="0" op_16_bw="0">
<![CDATA[
codeRepl:4  call void (...)* @_ssdm_op_SpecInterface(i16* %res_V_data_3_V, [8 x i8]* @ap_fifo_str, i32 0, i32 0, [1 x i8]* @p_str446, i32 0, i32 0, [1 x i8]* @p_str447, [1 x i8]* @p_str448, [1 x i8]* @p_str449, i32 2, i32 2, i32 16, i32 16, [1 x i8]* @p_str450, [1 x i8]* @p_str451)

]]></Node>
<StgValue><ssdm name="specinterface_ln0"/></StgValue>
</operation>

<operation id="11" st_id="1" stage="1" lat="1">
<core>NULL</core>
<MemPortIdVec></MemPortIdVec>
<condition id="-1">
<or_exp><and_exp></and_exp></or_exp>
</condition>

<Node id="57" bw="0" op_0_bw="0" op_1_bw="16" op_2_bw="0" op_3_bw="32" op_4_bw="32" op_5_bw="0" op_6_bw="32" op_7_bw="32" op_8_bw="0" op_9_bw="0" op_10_bw="0" op_11_bw="32" op_12_bw="32" op_13_bw="32" op_14_bw="32" op_15_bw="0" op_16_bw="0">
<![CDATA[
codeRepl:5  call void (...)* @_ssdm_op_SpecInterface(i16* %res_V_data_2_V, [8 x i8]* @ap_fifo_str, i32 0, i32 0, [1 x i8]* @p_str439, i32 0, i32 0, [1 x i8]* @p_str440, [1 x i8]* @p_str441, [1 x i8]* @p_str442, i32 2, i32 2, i32 16, i32 16, [1 x i8]* @p_str443, [1 x i8]* @p_str444)

]]></Node>
<StgValue><ssdm name="specinterface_ln0"/></StgValue>
</operation>

<operation id="12" st_id="1" stage="1" lat="1">
<core>NULL</core>
<MemPortIdVec></MemPortIdVec>
<condition id="-1">
<or_exp><and_exp></and_exp></or_exp>
</condition>

<Node id="58" bw="0" op_0_bw="0" op_1_bw="16" op_2_bw="0" op_3_bw="32" op_4_bw="32" op_5_bw="0" op_6_bw="32" op_7_bw="32" op_8_bw="0" op_9_bw="0" op_10_bw="0" op_11_bw="32" op_12_bw="32" op_13_bw="32" op_14_bw="32" op_15_bw="0" op_16_bw="0">
<![CDATA[
codeRepl:6  call void (...)* @_ssdm_op_SpecInterface(i16* %res_V_data_1_V, [8 x i8]* @ap_fifo_str, i32 0, i32 0, [1 x i8]* @p_str432, i32 0, i32 0, [1 x i8]* @p_str433, [1 x i8]* @p_str434, [1 x i8]* @p_str435, i32 2, i32 2, i32 16, i32 16, [1 x i8]* @p_str436, [1 x i8]* @p_str437)

]]></Node>
<StgValue><ssdm name="specinterface_ln0"/></StgValue>
</operation>

<operation id="13" st_id="1" stage="1" lat="1">
<core>NULL</core>
<MemPortIdVec></MemPortIdVec>
<condition id="-1">
<or_exp><and_exp></and_exp></or_exp>
</condition>

<Node id="59" bw="0" op_0_bw="0" op_1_bw="16" op_2_bw="0" op_3_bw="32" op_4_bw="32" op_5_bw="0" op_6_bw="32" op_7_bw="32" op_8_bw="0" op_9_bw="0" op_10_bw="0" op_11_bw="32" op_12_bw="32" op_13_bw="32" op_14_bw="32" op_15_bw="0" op_16_bw="0">
<![CDATA[
codeRepl:7  call void (...)* @_ssdm_op_SpecInterface(i16* %res_V_data_0_V, [8 x i8]* @ap_fifo_str, i32 0, i32 0, [1 x i8]* @p_str425, i32 0, i32 0, [1 x i8]* @p_str426, [1 x i8]* @p_str427, [1 x i8]* @p_str428, i32 2, i32 2, i32 16, i32 16, [1 x i8]* @p_str429, [1 x i8]* @p_str430)

]]></Node>
<StgValue><ssdm name="specinterface_ln0"/></StgValue>
</operation>

<operation id="14" st_id="1" stage="1" lat="1">
<core>NULL</core>
<MemPortIdVec></MemPortIdVec>
<condition id="-1">
<or_exp><and_exp></and_exp></or_exp>
</condition>

<Node id="60" bw="0" op_0_bw="0" op_1_bw="16" op_2_bw="0" op_3_bw="32" op_4_bw="32" op_5_bw="0" op_6_bw="32" op_7_bw="32" op_8_bw="0" op_9_bw="0" op_10_bw="0" op_11_bw="32" op_12_bw="32" op_13_bw="32" op_14_bw="32" op_15_bw="0" op_16_bw="0">
<![CDATA[
codeRepl:8  call void (...)* @_ssdm_op_SpecInterface(i16* %data_V_data_3_V, [8 x i8]* @ap_fifo_str, i32 0, i32 0, [1 x i8]* @p_str418, i32 0, i32 0, [1 x i8]* @p_str419, [1 x i8]* @p_str420, [1 x i8]* @p_str421, i32 2, i32 2, i32 16, i32 16, [1 x i8]* @p_str422, [1 x i8]* @p_str423)

]]></Node>
<StgValue><ssdm name="specinterface_ln0"/></StgValue>
</operation>

<operation id="15" st_id="1" stage="1" lat="1">
<core>NULL</core>
<MemPortIdVec></MemPortIdVec>
<condition id="-1">
<or_exp><and_exp></and_exp></or_exp>
</condition>

<Node id="61" bw="0" op_0_bw="0" op_1_bw="16" op_2_bw="0" op_3_bw="32" op_4_bw="32" op_5_bw="0" op_6_bw="32" op_7_bw="32" op_8_bw="0" op_9_bw="0" op_10_bw="0" op_11_bw="32" op_12_bw="32" op_13_bw="32" op_14_bw="32" op_15_bw="0" op_16_bw="0">
<![CDATA[
codeRepl:9  call void (...)* @_ssdm_op_SpecInterface(i16* %data_V_data_2_V, [8 x i8]* @ap_fifo_str, i32 0, i32 0, [1 x i8]* @p_str411, i32 0, i32 0, [1 x i8]* @p_str412, [1 x i8]* @p_str413, [1 x i8]* @p_str414, i32 2, i32 2, i32 16, i32 16, [1 x i8]* @p_str415, [1 x i8]* @p_str416)

]]></Node>
<StgValue><ssdm name="specinterface_ln0"/></StgValue>
</operation>

<operation id="16" st_id="1" stage="1" lat="1">
<core>NULL</core>
<MemPortIdVec></MemPortIdVec>
<condition id="-1">
<or_exp><and_exp></and_exp></or_exp>
</condition>

<Node id="62" bw="0" op_0_bw="0" op_1_bw="16" op_2_bw="0" op_3_bw="32" op_4_bw="32" op_5_bw="0" op_6_bw="32" op_7_bw="32" op_8_bw="0" op_9_bw="0" op_10_bw="0" op_11_bw="32" op_12_bw="32" op_13_bw="32" op_14_bw="32" op_15_bw="0" op_16_bw="0">
<![CDATA[
codeRepl:10  call void (...)* @_ssdm_op_SpecInterface(i16* %data_V_data_1_V, [8 x i8]* @ap_fifo_str, i32 0, i32 0, [1 x i8]* @p_str404, i32 0, i32 0, [1 x i8]* @p_str405, [1 x i8]* @p_str406, [1 x i8]* @p_str407, i32 2, i32 2, i32 16, i32 16, [1 x i8]* @p_str408, [1 x i8]* @p_str409)

]]></Node>
<StgValue><ssdm name="specinterface_ln0"/></StgValue>
</operation>

<operation id="17" st_id="1" stage="1" lat="1">
<core>NULL</core>
<MemPortIdVec></MemPortIdVec>
<condition id="-1">
<or_exp><and_exp></and_exp></or_exp>
</condition>

<Node id="63" bw="0" op_0_bw="0" op_1_bw="16" op_2_bw="0" op_3_bw="32" op_4_bw="32" op_5_bw="0" op_6_bw="32" op_7_bw="32" op_8_bw="0" op_9_bw="0" op_10_bw="0" op_11_bw="32" op_12_bw="32" op_13_bw="32" op_14_bw="32" op_15_bw="0" op_16_bw="0">
<![CDATA[
codeRepl:11  call void (...)* @_ssdm_op_SpecInterface(i16* %data_V_data_0_V, [8 x i8]* @ap_fifo_str, i32 0, i32 0, [1 x i8]* @p_str397, i32 0, i32 0, [1 x i8]* @p_str398, [1 x i8]* @p_str399, [1 x i8]* @p_str400, i32 2, i32 2, i32 16, i32 16, [1 x i8]* @p_str401, [1 x i8]* @p_str402)

]]></Node>
<StgValue><ssdm name="specinterface_ln0"/></StgValue>
</operation>

<operation id="18" st_id="1" stage="1" lat="1">
<core>NULL</core>
<MemPortIdVec></MemPortIdVec>
<condition id="-1">
<or_exp><and_exp></and_exp></or_exp>
</condition>

<Node id="64" bw="0" op_0_bw="0">
<![CDATA[
codeRepl:12  br label %0

]]></Node>
<StgValue><ssdm name="br_ln79"/></StgValue>
</operation>
</state>

<state id="2" st_id="2">

<operation id="19" st_id="2" stage="1" lat="1">
<core>NULL</core>
<MemPortIdVec></MemPortIdVec>
<condition id="-1">
<or_exp><and_exp></and_exp></or_exp>
</condition>

<Node id="66" bw="6" op_0_bw="6" op_1_bw="0" op_2_bw="6" op_3_bw="0">
<![CDATA[
:0  %indvar_flatten = phi i6 [ 0, %codeRepl ], [ %add_ln79, %hls_label_7 ]

]]></Node>
<StgValue><ssdm name="indvar_flatten"/></StgValue>
</operation>

<operation id="20" st_id="2" stage="1" lat="1">
<core>Cmp</core>
<MemPortIdVec></MemPortIdVec>
<condition id="-1">
<or_exp><and_exp></and_exp></or_exp>
</condition>

<Node id="67" bw="1" op_0_bw="6" op_1_bw="6">
<![CDATA[
:1  %icmp_ln79 = icmp eq i6 %indvar_flatten, -28

]]></Node>
<StgValue><ssdm name="icmp_ln79"/></StgValue>
</operation>

<operation id="21" st_id="2" stage="1" lat="1">
<core>AddSub</core>
<MemPortIdVec></MemPortIdVec>
<condition id="-1">
<or_exp><and_exp></and_exp></or_exp>
</condition>

<Node id="68" bw="6" op_0_bw="6" op_1_bw="6">
<![CDATA[
:2  %add_ln79 = add i6 %indvar_flatten, 1

]]></Node>
<StgValue><ssdm name="add_ln79"/></StgValue>
</operation>

<operation id="22" st_id="2" stage="1" lat="1">
<core>NULL</core>
<MemPortIdVec></MemPortIdVec>
<condition id="-1">
<or_exp><and_exp></and_exp></or_exp>
</condition>

<Node id="69" bw="0" op_0_bw="1" op_1_bw="0" op_2_bw="0">
<![CDATA[
:3  br i1 %icmp_ln79, label %"conv_2d_buffer_cl<array<ap_fixed<16, 6, 5, 3, 0>, 4u>, array<ap_fixed<16, 6, 5, 3, 0>, 8u>, config5>.exit", label %hls_label_7

]]></Node>
<StgValue><ssdm name="br_ln79"/></StgValue>
</operation>
</state>

<state id="3" st_id="3">

<operation id="23" st_id="3" stage="1" lat="1">
<core>FIFO</core>
<MemPortIdVec></MemPortIdVec>
<condition id="-1">
<or_exp><and_exp><literal name="icmp_ln79" val="0"/>
</and_exp></or_exp>
</condition>

<Node id="77" bw="64" op_0_bw="64" op_1_bw="16" op_2_bw="16" op_3_bw="16" op_4_bw="16">
<![CDATA[
hls_label_7:6  %empty_95 = call { i16, i16, i16, i16 } @_ssdm_op_Read.ap_fifo.volatile.i16P.i16P.i16P.i16P(i16* %data_V_data_0_V, i16* %data_V_data_1_V, i16* %data_V_data_2_V, i16* %data_V_data_3_V)

]]></Node>
<StgValue><ssdm name="empty_95"/></StgValue>
</operation>

<operation id="24" st_id="3" stage="1" lat="1">
<core>NULL</core>
<MemPortIdVec></MemPortIdVec>
<condition id="-1">
<or_exp><and_exp><literal name="icmp_ln79" val="0"/>
</and_exp></or_exp>
</condition>

<Node id="78" bw="16" op_0_bw="64">
<![CDATA[
hls_label_7:7  %tmp_data_0_V = extractvalue { i16, i16, i16, i16 } %empty_95, 0

]]></Node>
<StgValue><ssdm name="tmp_data_0_V"/></StgValue>
</operation>

<operation id="25" st_id="3" stage="1" lat="1">
<core>NULL</core>
<MemPortIdVec></MemPortIdVec>
<condition id="-1">
<or_exp><and_exp><literal name="icmp_ln79" val="0"/>
</and_exp></or_exp>
</condition>

<Node id="79" bw="16" op_0_bw="64">
<![CDATA[
hls_label_7:8  %tmp_data_1_V = extractvalue { i16, i16, i16, i16 } %empty_95, 1

]]></Node>
<StgValue><ssdm name="tmp_data_1_V"/></StgValue>
</operation>

<operation id="26" st_id="3" stage="1" lat="1">
<core>NULL</core>
<MemPortIdVec></MemPortIdVec>
<condition id="-1">
<or_exp><and_exp><literal name="icmp_ln79" val="0"/>
</and_exp></or_exp>
</condition>

<Node id="80" bw="16" op_0_bw="64">
<![CDATA[
hls_label_7:9  %tmp_data_2_V = extractvalue { i16, i16, i16, i16 } %empty_95, 2

]]></Node>
<StgValue><ssdm name="tmp_data_2_V"/></StgValue>
</operation>

<operation id="27" st_id="3" stage="1" lat="1">
<core>NULL</core>
<MemPortIdVec></MemPortIdVec>
<condition id="-1">
<or_exp><and_exp><literal name="icmp_ln79" val="0"/>
</and_exp></or_exp>
</condition>

<Node id="81" bw="16" op_0_bw="64">
<![CDATA[
hls_label_7:10  %tmp_data_3_V = extractvalue { i16, i16, i16, i16 } %empty_95, 3

]]></Node>
<StgValue><ssdm name="tmp_data_3_V"/></StgValue>
</operation>

<operation id="28" st_id="3" stage="2" lat="2">
<core></core>
<MemPortIdVec></MemPortIdVec>
<condition id="-1">
<or_exp><and_exp><literal name="icmp_ln79" val="0"/>
</and_exp></or_exp>
</condition>

<Node id="82" bw="0" op_0_bw="0" op_1_bw="16" op_2_bw="16" op_3_bw="16" op_4_bw="16" op_5_bw="16" op_6_bw="16" op_7_bw="16" op_8_bw="16" op_9_bw="16" op_10_bw="16" op_11_bw="16" op_12_bw="16" op_13_bw="16" op_14_bw="16" op_15_bw="16" op_16_bw="16" op_17_bw="16" op_18_bw="16" op_19_bw="16" op_20_bw="16" op_21_bw="16" op_22_bw="16" op_23_bw="16" op_24_bw="16" op_25_bw="16" op_26_bw="16" op_27_bw="16" op_28_bw="16" op_29_bw="16" op_30_bw="16" op_31_bw="16" op_32_bw="16" op_33_bw="16" op_34_bw="16" op_35_bw="16" op_36_bw="16" op_37_bw="16" op_38_bw="16" op_39_bw="16" op_40_bw="16" op_41_bw="16" op_42_bw="16" op_43_bw="16" op_44_bw="16" op_45_bw="32" op_46_bw="32" op_47_bw="32" op_48_bw="32">
<![CDATA[
hls_label_7:11  call fastcc void @"compute_output_buffer_2d<array,array<ap_fixed<16,6,5,3,0>,8u>,config5>"(i16 %tmp_data_0_V, i16 %tmp_data_1_V, i16 %tmp_data_2_V, i16 %tmp_data_3_V, i16* %res_V_data_0_V, i16* %res_V_data_1_V, i16* %res_V_data_2_V, i16* %res_V_data_3_V, i16* %res_V_data_4_V, i16* %res_V_data_5_V, i16* %res_V_data_6_V, i16* %res_V_data_7_V)

]]></Node>
<StgValue><ssdm name="call_ln87"/></StgValue>
</operation>
</state>

<state id="4" st_id="4">

<operation id="29" st_id="4" stage="1" lat="1">
<core>NULL</core>
<MemPortIdVec></MemPortIdVec>
<condition id="-1">
<or_exp><and_exp><literal name="icmp_ln79" val="0"/>
</and_exp></or_exp>
</condition>

<Node id="71" bw="0" op_0_bw="0" op_1_bw="0">
<![CDATA[
hls_label_7:0  call void (...)* @_ssdm_op_SpecLoopName([31 x i8]* @ReadInputHeight_ReadInputWidth_str)

]]></Node>
<StgValue><ssdm name="specloopname_ln0"/></StgValue>
</operation>

<operation id="30" st_id="4" stage="1" lat="1">
<core>NULL</core>
<MemPortIdVec></MemPortIdVec>
<condition id="-1">
<or_exp><and_exp><literal name="icmp_ln79" val="0"/>
</and_exp></or_exp>
</condition>

<Node id="72" bw="32" op_0_bw="32" op_1_bw="64" op_2_bw="64" op_3_bw="64">
<![CDATA[
hls_label_7:1  %empty = call i32 (...)* @_ssdm_op_SpecLoopTripCount(i64 36, i64 36, i64 36)

]]></Node>
<StgValue><ssdm name="empty"/></StgValue>
</operation>

<operation id="31" st_id="4" stage="1" lat="1">
<core>NULL</core>
<MemPortIdVec></MemPortIdVec>
<condition id="-1">
<or_exp><and_exp><literal name="icmp_ln79" val="0"/>
</and_exp></or_exp>
</condition>

<Node id="73" bw="0" op_0_bw="0" op_1_bw="0">
<![CDATA[
hls_label_7:2  call void (...)* @_ssdm_op_SpecLoopName([15 x i8]* @p_str38) nounwind

]]></Node>
<StgValue><ssdm name="specloopname_ln81"/></StgValue>
</operation>

<operation id="32" st_id="4" stage="1" lat="1">
<core>NULL</core>
<MemPortIdVec></MemPortIdVec>
<condition id="-1">
<or_exp><and_exp><literal name="icmp_ln79" val="0"/>
</and_exp></or_exp>
</condition>

<Node id="74" bw="32" op_0_bw="32" op_1_bw="0">
<![CDATA[
hls_label_7:3  %tmp_s = call i32 (...)* @_ssdm_op_SpecRegionBegin([12 x i8]* @p_str51)

]]></Node>
<StgValue><ssdm name="tmp_s"/></StgValue>
</operation>

<operation id="33" st_id="4" stage="1" lat="1">
<core>NULL</core>
<MemPortIdVec></MemPortIdVec>
<condition id="-1">
<or_exp><and_exp><literal name="icmp_ln79" val="0"/>
</and_exp></or_exp>
</condition>

<Node id="75" bw="0" op_0_bw="0" op_1_bw="32" op_2_bw="32" op_3_bw="32" op_4_bw="32" op_5_bw="0">
<![CDATA[
hls_label_7:4  call void (...)* @_ssdm_op_SpecPipeline(i32 1, i32 1, i32 1, i32 0, [1 x i8]* @p_str10) nounwind

]]></Node>
<StgValue><ssdm name="specpipeline_ln84"/></StgValue>
</operation>

<operation id="34" st_id="4" stage="1" lat="1">
<core>NULL</core>
<MemPortIdVec></MemPortIdVec>
<condition id="-1">
<or_exp><and_exp><literal name="icmp_ln79" val="0"/>
</and_exp></or_exp>
</condition>

<Node id="76" bw="32" op_0_bw="32" op_1_bw="0" op_2_bw="32">
<![CDATA[
hls_label_7:5  %empty_94 = call i32 (...)* @_ssdm_op_SpecRegionEnd([12 x i8]* @p_str51, i32 %tmp_s)

]]></Node>
<StgValue><ssdm name="empty_94"/></StgValue>
</operation>

<operation id="35" st_id="4" stage="1" lat="2">
<core></core>
<MemPortIdVec></MemPortIdVec>
<condition id="-1">
<or_exp><and_exp><literal name="icmp_ln79" val="0"/>
</and_exp></or_exp>
</condition>

<Node id="82" bw="0" op_0_bw="0" op_1_bw="16" op_2_bw="16" op_3_bw="16" op_4_bw="16" op_5_bw="16" op_6_bw="16" op_7_bw="16" op_8_bw="16" op_9_bw="16" op_10_bw="16" op_11_bw="16" op_12_bw="16" op_13_bw="16" op_14_bw="16" op_15_bw="16" op_16_bw="16" op_17_bw="16" op_18_bw="16" op_19_bw="16" op_20_bw="16" op_21_bw="16" op_22_bw="16" op_23_bw="16" op_24_bw="16" op_25_bw="16" op_26_bw="16" op_27_bw="16" op_28_bw="16" op_29_bw="16" op_30_bw="16" op_31_bw="16" op_32_bw="16" op_33_bw="16" op_34_bw="16" op_35_bw="16" op_36_bw="16" op_37_bw="16" op_38_bw="16" op_39_bw="16" op_40_bw="16" op_41_bw="16" op_42_bw="16" op_43_bw="16" op_44_bw="16" op_45_bw="32" op_46_bw="32" op_47_bw="32" op_48_bw="32">
<![CDATA[
hls_label_7:11  call fastcc void @"compute_output_buffer_2d<array,array<ap_fixed<16,6,5,3,0>,8u>,config5>"(i16 %tmp_data_0_V, i16 %tmp_data_1_V, i16 %tmp_data_2_V, i16 %tmp_data_3_V, i16* %res_V_data_0_V, i16* %res_V_data_1_V, i16* %res_V_data_2_V, i16* %res_V_data_3_V, i16* %res_V_data_4_V, i16* %res_V_data_5_V, i16* %res_V_data_6_V, i16* %res_V_data_7_V)

]]></Node>
<StgValue><ssdm name="call_ln87"/></StgValue>
</operation>

<operation id="36" st_id="4" stage="1" lat="1">
<core>NULL</core>
<MemPortIdVec></MemPortIdVec>
<condition id="-1">
<or_exp><and_exp><literal name="icmp_ln79" val="0"/>
</and_exp></or_exp>
</condition>

<Node id="83" bw="0" op_0_bw="0">
<![CDATA[
hls_label_7:12  br label %0

]]></Node>
<StgValue><ssdm name="br_ln0"/></StgValue>
</operation>
</state>

<state id="5" st_id="5">

<operation id="37" st_id="5" stage="1" lat="1">
<core>NULL</core>
<MemPortIdVec></MemPortIdVec>
<condition id="-1">
<or_exp><and_exp></and_exp></or_exp>
</condition>

<Node id="85" bw="0">
<![CDATA[
conv_2d_buffer_cl<array<ap_fixed<16, 6, 5, 3, 0>, 4u>, array<ap_fixed<16, 6, 5, 3, 0>, 8u>, config5>.exit:0  ret void

]]></Node>
<StgValue><ssdm name="ret_ln109"/></StgValue>
</operation>
</state>
</state_list>


<ports>
<port id="48" name="data_V_data_0_V" dir="0" iftype="3">
<core>FIFO</core><StgValue><ssdm name="data_V_data_0_V"/></StgValue>
</port>
<port id="49" name="data_V_data_1_V" dir="0" iftype="3">
<core>FIFO</core><StgValue><ssdm name="data_V_data_1_V"/></StgValue>
</port>
<port id="50" name="data_V_data_2_V" dir="0" iftype="3">
<core>FIFO</core><StgValue><ssdm name="data_V_data_2_V"/></StgValue>
</port>
<port id="51" name="data_V_data_3_V" dir="0" iftype="3">
<core>FIFO</core><StgValue><ssdm name="data_V_data_3_V"/></StgValue>
</port>
<port id="52" name="res_V_data_0_V" dir="1" iftype="3">
<core>FIFO</core><StgValue><ssdm name="res_V_data_0_V"/></StgValue>
</port>
<port id="53" name="res_V_data_1_V" dir="1" iftype="3">
<core>FIFO</core><StgValue><ssdm name="res_V_data_1_V"/></StgValue>
</port>
<port id="54" name="res_V_data_2_V" dir="1" iftype="3">
<core>FIFO</core><StgValue><ssdm name="res_V_data_2_V"/></StgValue>
</port>
<port id="55" name="res_V_data_3_V" dir="1" iftype="3">
<core>FIFO</core><StgValue><ssdm name="res_V_data_3_V"/></StgValue>
</port>
<port id="56" name="res_V_data_4_V" dir="1" iftype="3">
<core>FIFO</core><StgValue><ssdm name="res_V_data_4_V"/></StgValue>
</port>
<port id="57" name="res_V_data_5_V" dir="1" iftype="3">
<core>FIFO</core><StgValue><ssdm name="res_V_data_5_V"/></StgValue>
</port>
<port id="58" name="res_V_data_6_V" dir="1" iftype="3">
<core>FIFO</core><StgValue><ssdm name="res_V_data_6_V"/></StgValue>
</port>
<port id="59" name="res_V_data_7_V" dir="1" iftype="3">
<core>FIFO</core><StgValue><ssdm name="res_V_data_7_V"/></StgValue>
</port>
<port id="60" name="kernel_data_V_1_4" dir="2" iftype="0">
<core>NULL</core><StgValue><ssdm name="kernel_data_V_1_4"/></StgValue>
</port>
<port id="61" name="kernel_data_V_1_5" dir="2" iftype="0">
<core>NULL</core><StgValue><ssdm name="kernel_data_V_1_5"/></StgValue>
</port>
<port id="62" name="kernel_data_V_1_6" dir="2" iftype="0">
<core>NULL</core><StgValue><ssdm name="kernel_data_V_1_6"/></StgValue>
</port>
<port id="63" name="kernel_data_V_1_7" dir="2" iftype="0">
<core>NULL</core><StgValue><ssdm name="kernel_data_V_1_7"/></StgValue>
</port>
<port id="64" name="kernel_data_V_1_8" dir="2" iftype="0">
<core>NULL</core><StgValue><ssdm name="kernel_data_V_1_8"/></StgValue>
</port>
<port id="65" name="kernel_data_V_1_9" dir="2" iftype="0">
<core>NULL</core><StgValue><ssdm name="kernel_data_V_1_9"/></StgValue>
</port>
<port id="66" name="kernel_data_V_1_10" dir="2" iftype="0">
<core>NULL</core><StgValue><ssdm name="kernel_data_V_1_10"/></StgValue>
</port>
<port id="67" name="kernel_data_V_1_11" dir="2" iftype="0">
<core>NULL</core><StgValue><ssdm name="kernel_data_V_1_11"/></StgValue>
</port>
<port id="68" name="kernel_data_V_1_16" dir="2" iftype="0">
<core>NULL</core><StgValue><ssdm name="kernel_data_V_1_16"/></StgValue>
</port>
<port id="69" name="kernel_data_V_1_17" dir="2" iftype="0">
<core>NULL</core><StgValue><ssdm name="kernel_data_V_1_17"/></StgValue>
</port>
<port id="70" name="kernel_data_V_1_18" dir="2" iftype="0">
<core>NULL</core><StgValue><ssdm name="kernel_data_V_1_18"/></StgValue>
</port>
<port id="71" name="kernel_data_V_1_19" dir="2" iftype="0">
<core>NULL</core><StgValue><ssdm name="kernel_data_V_1_19"/></StgValue>
</port>
<port id="72" name="kernel_data_V_1_20" dir="2" iftype="0">
<core>NULL</core><StgValue><ssdm name="kernel_data_V_1_20"/></StgValue>
</port>
<port id="73" name="kernel_data_V_1_21" dir="2" iftype="0">
<core>NULL</core><StgValue><ssdm name="kernel_data_V_1_21"/></StgValue>
</port>
<port id="74" name="kernel_data_V_1_22" dir="2" iftype="0">
<core>NULL</core><StgValue><ssdm name="kernel_data_V_1_22"/></StgValue>
</port>
<port id="75" name="kernel_data_V_1_23" dir="2" iftype="0">
<core>NULL</core><StgValue><ssdm name="kernel_data_V_1_23"/></StgValue>
</port>
<port id="76" name="kernel_data_V_1_28" dir="2" iftype="0">
<core>NULL</core><StgValue><ssdm name="kernel_data_V_1_28"/></StgValue>
</port>
<port id="77" name="kernel_data_V_1_29" dir="2" iftype="0">
<core>NULL</core><StgValue><ssdm name="kernel_data_V_1_29"/></StgValue>
</port>
<port id="78" name="kernel_data_V_1_30" dir="2" iftype="0">
<core>NULL</core><StgValue><ssdm name="kernel_data_V_1_30"/></StgValue>
</port>
<port id="79" name="kernel_data_V_1_31" dir="2" iftype="0">
<core>NULL</core><StgValue><ssdm name="kernel_data_V_1_31"/></StgValue>
</port>
<port id="80" name="kernel_data_V_1_32" dir="2" iftype="0">
<core>NULL</core><StgValue><ssdm name="kernel_data_V_1_32"/></StgValue>
</port>
<port id="81" name="kernel_data_V_1_33" dir="2" iftype="0">
<core>NULL</core><StgValue><ssdm name="kernel_data_V_1_33"/></StgValue>
</port>
<port id="82" name="kernel_data_V_1_34" dir="2" iftype="0">
<core>NULL</core><StgValue><ssdm name="kernel_data_V_1_34"/></StgValue>
</port>
<port id="83" name="kernel_data_V_1_35" dir="2" iftype="0">
<core>NULL</core><StgValue><ssdm name="kernel_data_V_1_35"/></StgValue>
</port>
<port id="84" name="line_buffer_Array_V_1_0_0" dir="3" iftype="1">
<core>ShiftReg</core><StgValue><ssdm name="line_buffer_Array_V_1_0_0"/><MemPortTyVec>2 </MemPortTyVec>
</StgValue>
</port>
<port id="85" name="line_buffer_Array_V_1_1_0" dir="3" iftype="1">
<core>ShiftReg</core><StgValue><ssdm name="line_buffer_Array_V_1_1_0"/><MemPortTyVec>2 </MemPortTyVec>
</StgValue>
</port>
<port id="86" name="line_buffer_Array_V_1_0_1" dir="3" iftype="1">
<core>ShiftReg</core><StgValue><ssdm name="line_buffer_Array_V_1_0_1"/><MemPortTyVec>2 </MemPortTyVec>
</StgValue>
</port>
<port id="87" name="line_buffer_Array_V_1_1_1" dir="3" iftype="1">
<core>ShiftReg</core><StgValue><ssdm name="line_buffer_Array_V_1_1_1"/><MemPortTyVec>2 </MemPortTyVec>
</StgValue>
</port>
<port id="88" name="line_buffer_Array_V_1_0_2" dir="3" iftype="1">
<core>ShiftReg</core><StgValue><ssdm name="line_buffer_Array_V_1_0_2"/><MemPortTyVec>2 </MemPortTyVec>
</StgValue>
</port>
<port id="89" name="line_buffer_Array_V_1_1_2" dir="3" iftype="1">
<core>ShiftReg</core><StgValue><ssdm name="line_buffer_Array_V_1_1_2"/><MemPortTyVec>2 </MemPortTyVec>
</StgValue>
</port>
<port id="90" name="line_buffer_Array_V_1_0_3" dir="3" iftype="1">
<core>ShiftReg</core><StgValue><ssdm name="line_buffer_Array_V_1_0_3"/><MemPortTyVec>2 </MemPortTyVec>
</StgValue>
</port>
<port id="91" name="line_buffer_Array_V_1_1_3" dir="3" iftype="1">
<core>ShiftReg</core><StgValue><ssdm name="line_buffer_Array_V_1_1_3"/><MemPortTyVec>2 </MemPortTyVec>
</StgValue>
</port>
<port id="92" name="sX_2" dir="2" iftype="0">
<core>NULL</core><StgValue><ssdm name="sX_2"/></StgValue>
</port>
<port id="93" name="sY_2" dir="2" iftype="0">
<core>NULL</core><StgValue><ssdm name="sY_2"/></StgValue>
</port>
<port id="94" name="pY_2" dir="2" iftype="0">
<core>NULL</core><StgValue><ssdm name="pY_2"/></StgValue>
</port>
<port id="95" name="pX_2" dir="2" iftype="0">
<core>NULL</core><StgValue><ssdm name="pX_2"/></StgValue>
</port>
</ports>


<dataflows>
<dataflow id="97" from="_ssdm_op_SpecInterface" to="specinterface_ln0" fromId="96" toId="6">
</dataflow>
<dataflow id="98" from="res_V_data_7_V" to="specinterface_ln0" fromId="59" toId="6">
</dataflow>
<dataflow id="100" from="ap_fifo_str" to="specinterface_ln0" fromId="99" toId="6">
</dataflow>
<dataflow id="102" from="StgValue_101" to="specinterface_ln0" fromId="101" toId="6">
</dataflow>
<dataflow id="103" from="StgValue_101" to="specinterface_ln0" fromId="101" toId="6">
</dataflow>
<dataflow id="105" from="p_str474" to="specinterface_ln0" fromId="104" toId="6">
</dataflow>
<dataflow id="106" from="StgValue_101" to="specinterface_ln0" fromId="101" toId="6">
</dataflow>
<dataflow id="107" from="StgValue_101" to="specinterface_ln0" fromId="101" toId="6">
</dataflow>
<dataflow id="109" from="p_str475" to="specinterface_ln0" fromId="108" toId="6">
</dataflow>
<dataflow id="111" from="p_str476" to="specinterface_ln0" fromId="110" toId="6">
</dataflow>
<dataflow id="113" from="p_str477" to="specinterface_ln0" fromId="112" toId="6">
</dataflow>
<dataflow id="115" from="StgValue_114" to="specinterface_ln0" fromId="114" toId="6">
</dataflow>
<dataflow id="116" from="StgValue_114" to="specinterface_ln0" fromId="114" toId="6">
</dataflow>
<dataflow id="118" from="StgValue_117" to="specinterface_ln0" fromId="117" toId="6">
</dataflow>
<dataflow id="119" from="StgValue_117" to="specinterface_ln0" fromId="117" toId="6">
</dataflow>
<dataflow id="121" from="p_str478" to="specinterface_ln0" fromId="120" toId="6">
</dataflow>
<dataflow id="123" from="p_str479" to="specinterface_ln0" fromId="122" toId="6">
</dataflow>
<dataflow id="124" from="_ssdm_op_SpecInterface" to="specinterface_ln0" fromId="96" toId="7">
</dataflow>
<dataflow id="125" from="res_V_data_6_V" to="specinterface_ln0" fromId="58" toId="7">
</dataflow>
<dataflow id="126" from="ap_fifo_str" to="specinterface_ln0" fromId="99" toId="7">
</dataflow>
<dataflow id="127" from="StgValue_101" to="specinterface_ln0" fromId="101" toId="7">
</dataflow>
<dataflow id="128" from="StgValue_101" to="specinterface_ln0" fromId="101" toId="7">
</dataflow>
<dataflow id="130" from="p_str467" to="specinterface_ln0" fromId="129" toId="7">
</dataflow>
<dataflow id="131" from="StgValue_101" to="specinterface_ln0" fromId="101" toId="7">
</dataflow>
<dataflow id="132" from="StgValue_101" to="specinterface_ln0" fromId="101" toId="7">
</dataflow>
<dataflow id="134" from="p_str468" to="specinterface_ln0" fromId="133" toId="7">
</dataflow>
<dataflow id="136" from="p_str469" to="specinterface_ln0" fromId="135" toId="7">
</dataflow>
<dataflow id="138" from="p_str470" to="specinterface_ln0" fromId="137" toId="7">
</dataflow>
<dataflow id="139" from="StgValue_114" to="specinterface_ln0" fromId="114" toId="7">
</dataflow>
<dataflow id="140" from="StgValue_114" to="specinterface_ln0" fromId="114" toId="7">
</dataflow>
<dataflow id="141" from="StgValue_117" to="specinterface_ln0" fromId="117" toId="7">
</dataflow>
<dataflow id="142" from="StgValue_117" to="specinterface_ln0" fromId="117" toId="7">
</dataflow>
<dataflow id="144" from="p_str471" to="specinterface_ln0" fromId="143" toId="7">
</dataflow>
<dataflow id="146" from="p_str472" to="specinterface_ln0" fromId="145" toId="7">
</dataflow>
<dataflow id="147" from="_ssdm_op_SpecInterface" to="specinterface_ln0" fromId="96" toId="8">
</dataflow>
<dataflow id="148" from="res_V_data_5_V" to="specinterface_ln0" fromId="57" toId="8">
</dataflow>
<dataflow id="149" from="ap_fifo_str" to="specinterface_ln0" fromId="99" toId="8">
</dataflow>
<dataflow id="150" from="StgValue_101" to="specinterface_ln0" fromId="101" toId="8">
</dataflow>
<dataflow id="151" from="StgValue_101" to="specinterface_ln0" fromId="101" toId="8">
</dataflow>
<dataflow id="153" from="p_str460" to="specinterface_ln0" fromId="152" toId="8">
</dataflow>
<dataflow id="154" from="StgValue_101" to="specinterface_ln0" fromId="101" toId="8">
</dataflow>
<dataflow id="155" from="StgValue_101" to="specinterface_ln0" fromId="101" toId="8">
</dataflow>
<dataflow id="157" from="p_str461" to="specinterface_ln0" fromId="156" toId="8">
</dataflow>
<dataflow id="159" from="p_str462" to="specinterface_ln0" fromId="158" toId="8">
</dataflow>
<dataflow id="161" from="p_str463" to="specinterface_ln0" fromId="160" toId="8">
</dataflow>
<dataflow id="162" from="StgValue_114" to="specinterface_ln0" fromId="114" toId="8">
</dataflow>
<dataflow id="163" from="StgValue_114" to="specinterface_ln0" fromId="114" toId="8">
</dataflow>
<dataflow id="164" from="StgValue_117" to="specinterface_ln0" fromId="117" toId="8">
</dataflow>
<dataflow id="165" from="StgValue_117" to="specinterface_ln0" fromId="117" toId="8">
</dataflow>
<dataflow id="167" from="p_str464" to="specinterface_ln0" fromId="166" toId="8">
</dataflow>
<dataflow id="169" from="p_str465" to="specinterface_ln0" fromId="168" toId="8">
</dataflow>
<dataflow id="170" from="_ssdm_op_SpecInterface" to="specinterface_ln0" fromId="96" toId="9">
</dataflow>
<dataflow id="171" from="res_V_data_4_V" to="specinterface_ln0" fromId="56" toId="9">
</dataflow>
<dataflow id="172" from="ap_fifo_str" to="specinterface_ln0" fromId="99" toId="9">
</dataflow>
<dataflow id="173" from="StgValue_101" to="specinterface_ln0" fromId="101" toId="9">
</dataflow>
<dataflow id="174" from="StgValue_101" to="specinterface_ln0" fromId="101" toId="9">
</dataflow>
<dataflow id="176" from="p_str453" to="specinterface_ln0" fromId="175" toId="9">
</dataflow>
<dataflow id="177" from="StgValue_101" to="specinterface_ln0" fromId="101" toId="9">
</dataflow>
<dataflow id="178" from="StgValue_101" to="specinterface_ln0" fromId="101" toId="9">
</dataflow>
<dataflow id="180" from="p_str454" to="specinterface_ln0" fromId="179" toId="9">
</dataflow>
<dataflow id="182" from="p_str455" to="specinterface_ln0" fromId="181" toId="9">
</dataflow>
<dataflow id="184" from="p_str456" to="specinterface_ln0" fromId="183" toId="9">
</dataflow>
<dataflow id="185" from="StgValue_114" to="specinterface_ln0" fromId="114" toId="9">
</dataflow>
<dataflow id="186" from="StgValue_114" to="specinterface_ln0" fromId="114" toId="9">
</dataflow>
<dataflow id="187" from="StgValue_117" to="specinterface_ln0" fromId="117" toId="9">
</dataflow>
<dataflow id="188" from="StgValue_117" to="specinterface_ln0" fromId="117" toId="9">
</dataflow>
<dataflow id="190" from="p_str457" to="specinterface_ln0" fromId="189" toId="9">
</dataflow>
<dataflow id="192" from="p_str458" to="specinterface_ln0" fromId="191" toId="9">
</dataflow>
<dataflow id="193" from="_ssdm_op_SpecInterface" to="specinterface_ln0" fromId="96" toId="10">
</dataflow>
<dataflow id="194" from="res_V_data_3_V" to="specinterface_ln0" fromId="55" toId="10">
</dataflow>
<dataflow id="195" from="ap_fifo_str" to="specinterface_ln0" fromId="99" toId="10">
</dataflow>
<dataflow id="196" from="StgValue_101" to="specinterface_ln0" fromId="101" toId="10">
</dataflow>
<dataflow id="197" from="StgValue_101" to="specinterface_ln0" fromId="101" toId="10">
</dataflow>
<dataflow id="199" from="p_str446" to="specinterface_ln0" fromId="198" toId="10">
</dataflow>
<dataflow id="200" from="StgValue_101" to="specinterface_ln0" fromId="101" toId="10">
</dataflow>
<dataflow id="201" from="StgValue_101" to="specinterface_ln0" fromId="101" toId="10">
</dataflow>
<dataflow id="203" from="p_str447" to="specinterface_ln0" fromId="202" toId="10">
</dataflow>
<dataflow id="205" from="p_str448" to="specinterface_ln0" fromId="204" toId="10">
</dataflow>
<dataflow id="207" from="p_str449" to="specinterface_ln0" fromId="206" toId="10">
</dataflow>
<dataflow id="208" from="StgValue_114" to="specinterface_ln0" fromId="114" toId="10">
</dataflow>
<dataflow id="209" from="StgValue_114" to="specinterface_ln0" fromId="114" toId="10">
</dataflow>
<dataflow id="210" from="StgValue_117" to="specinterface_ln0" fromId="117" toId="10">
</dataflow>
<dataflow id="211" from="StgValue_117" to="specinterface_ln0" fromId="117" toId="10">
</dataflow>
<dataflow id="213" from="p_str450" to="specinterface_ln0" fromId="212" toId="10">
</dataflow>
<dataflow id="215" from="p_str451" to="specinterface_ln0" fromId="214" toId="10">
</dataflow>
<dataflow id="216" from="_ssdm_op_SpecInterface" to="specinterface_ln0" fromId="96" toId="11">
</dataflow>
<dataflow id="217" from="res_V_data_2_V" to="specinterface_ln0" fromId="54" toId="11">
</dataflow>
<dataflow id="218" from="ap_fifo_str" to="specinterface_ln0" fromId="99" toId="11">
</dataflow>
<dataflow id="219" from="StgValue_101" to="specinterface_ln0" fromId="101" toId="11">
</dataflow>
<dataflow id="220" from="StgValue_101" to="specinterface_ln0" fromId="101" toId="11">
</dataflow>
<dataflow id="222" from="p_str439" to="specinterface_ln0" fromId="221" toId="11">
</dataflow>
<dataflow id="223" from="StgValue_101" to="specinterface_ln0" fromId="101" toId="11">
</dataflow>
<dataflow id="224" from="StgValue_101" to="specinterface_ln0" fromId="101" toId="11">
</dataflow>
<dataflow id="226" from="p_str440" to="specinterface_ln0" fromId="225" toId="11">
</dataflow>
<dataflow id="228" from="p_str441" to="specinterface_ln0" fromId="227" toId="11">
</dataflow>
<dataflow id="230" from="p_str442" to="specinterface_ln0" fromId="229" toId="11">
</dataflow>
<dataflow id="231" from="StgValue_114" to="specinterface_ln0" fromId="114" toId="11">
</dataflow>
<dataflow id="232" from="StgValue_114" to="specinterface_ln0" fromId="114" toId="11">
</dataflow>
<dataflow id="233" from="StgValue_117" to="specinterface_ln0" fromId="117" toId="11">
</dataflow>
<dataflow id="234" from="StgValue_117" to="specinterface_ln0" fromId="117" toId="11">
</dataflow>
<dataflow id="236" from="p_str443" to="specinterface_ln0" fromId="235" toId="11">
</dataflow>
<dataflow id="238" from="p_str444" to="specinterface_ln0" fromId="237" toId="11">
</dataflow>
<dataflow id="239" from="_ssdm_op_SpecInterface" to="specinterface_ln0" fromId="96" toId="12">
</dataflow>
<dataflow id="240" from="res_V_data_1_V" to="specinterface_ln0" fromId="53" toId="12">
</dataflow>
<dataflow id="241" from="ap_fifo_str" to="specinterface_ln0" fromId="99" toId="12">
</dataflow>
<dataflow id="242" from="StgValue_101" to="specinterface_ln0" fromId="101" toId="12">
</dataflow>
<dataflow id="243" from="StgValue_101" to="specinterface_ln0" fromId="101" toId="12">
</dataflow>
<dataflow id="245" from="p_str432" to="specinterface_ln0" fromId="244" toId="12">
</dataflow>
<dataflow id="246" from="StgValue_101" to="specinterface_ln0" fromId="101" toId="12">
</dataflow>
<dataflow id="247" from="StgValue_101" to="specinterface_ln0" fromId="101" toId="12">
</dataflow>
<dataflow id="249" from="p_str433" to="specinterface_ln0" fromId="248" toId="12">
</dataflow>
<dataflow id="251" from="p_str434" to="specinterface_ln0" fromId="250" toId="12">
</dataflow>
<dataflow id="253" from="p_str435" to="specinterface_ln0" fromId="252" toId="12">
</dataflow>
<dataflow id="254" from="StgValue_114" to="specinterface_ln0" fromId="114" toId="12">
</dataflow>
<dataflow id="255" from="StgValue_114" to="specinterface_ln0" fromId="114" toId="12">
</dataflow>
<dataflow id="256" from="StgValue_117" to="specinterface_ln0" fromId="117" toId="12">
</dataflow>
<dataflow id="257" from="StgValue_117" to="specinterface_ln0" fromId="117" toId="12">
</dataflow>
<dataflow id="259" from="p_str436" to="specinterface_ln0" fromId="258" toId="12">
</dataflow>
<dataflow id="261" from="p_str437" to="specinterface_ln0" fromId="260" toId="12">
</dataflow>
<dataflow id="262" from="_ssdm_op_SpecInterface" to="specinterface_ln0" fromId="96" toId="13">
</dataflow>
<dataflow id="263" from="res_V_data_0_V" to="specinterface_ln0" fromId="52" toId="13">
</dataflow>
<dataflow id="264" from="ap_fifo_str" to="specinterface_ln0" fromId="99" toId="13">
</dataflow>
<dataflow id="265" from="StgValue_101" to="specinterface_ln0" fromId="101" toId="13">
</dataflow>
<dataflow id="266" from="StgValue_101" to="specinterface_ln0" fromId="101" toId="13">
</dataflow>
<dataflow id="268" from="p_str425" to="specinterface_ln0" fromId="267" toId="13">
</dataflow>
<dataflow id="269" from="StgValue_101" to="specinterface_ln0" fromId="101" toId="13">
</dataflow>
<dataflow id="270" from="StgValue_101" to="specinterface_ln0" fromId="101" toId="13">
</dataflow>
<dataflow id="272" from="p_str426" to="specinterface_ln0" fromId="271" toId="13">
</dataflow>
<dataflow id="274" from="p_str427" to="specinterface_ln0" fromId="273" toId="13">
</dataflow>
<dataflow id="276" from="p_str428" to="specinterface_ln0" fromId="275" toId="13">
</dataflow>
<dataflow id="277" from="StgValue_114" to="specinterface_ln0" fromId="114" toId="13">
</dataflow>
<dataflow id="278" from="StgValue_114" to="specinterface_ln0" fromId="114" toId="13">
</dataflow>
<dataflow id="279" from="StgValue_117" to="specinterface_ln0" fromId="117" toId="13">
</dataflow>
<dataflow id="280" from="StgValue_117" to="specinterface_ln0" fromId="117" toId="13">
</dataflow>
<dataflow id="282" from="p_str429" to="specinterface_ln0" fromId="281" toId="13">
</dataflow>
<dataflow id="284" from="p_str430" to="specinterface_ln0" fromId="283" toId="13">
</dataflow>
<dataflow id="285" from="_ssdm_op_SpecInterface" to="specinterface_ln0" fromId="96" toId="14">
</dataflow>
<dataflow id="286" from="data_V_data_3_V" to="specinterface_ln0" fromId="51" toId="14">
</dataflow>
<dataflow id="287" from="ap_fifo_str" to="specinterface_ln0" fromId="99" toId="14">
</dataflow>
<dataflow id="288" from="StgValue_101" to="specinterface_ln0" fromId="101" toId="14">
</dataflow>
<dataflow id="289" from="StgValue_101" to="specinterface_ln0" fromId="101" toId="14">
</dataflow>
<dataflow id="291" from="p_str418" to="specinterface_ln0" fromId="290" toId="14">
</dataflow>
<dataflow id="292" from="StgValue_101" to="specinterface_ln0" fromId="101" toId="14">
</dataflow>
<dataflow id="293" from="StgValue_101" to="specinterface_ln0" fromId="101" toId="14">
</dataflow>
<dataflow id="295" from="p_str419" to="specinterface_ln0" fromId="294" toId="14">
</dataflow>
<dataflow id="297" from="p_str420" to="specinterface_ln0" fromId="296" toId="14">
</dataflow>
<dataflow id="299" from="p_str421" to="specinterface_ln0" fromId="298" toId="14">
</dataflow>
<dataflow id="300" from="StgValue_114" to="specinterface_ln0" fromId="114" toId="14">
</dataflow>
<dataflow id="301" from="StgValue_114" to="specinterface_ln0" fromId="114" toId="14">
</dataflow>
<dataflow id="302" from="StgValue_117" to="specinterface_ln0" fromId="117" toId="14">
</dataflow>
<dataflow id="303" from="StgValue_117" to="specinterface_ln0" fromId="117" toId="14">
</dataflow>
<dataflow id="305" from="p_str422" to="specinterface_ln0" fromId="304" toId="14">
</dataflow>
<dataflow id="307" from="p_str423" to="specinterface_ln0" fromId="306" toId="14">
</dataflow>
<dataflow id="308" from="_ssdm_op_SpecInterface" to="specinterface_ln0" fromId="96" toId="15">
</dataflow>
<dataflow id="309" from="data_V_data_2_V" to="specinterface_ln0" fromId="50" toId="15">
</dataflow>
<dataflow id="310" from="ap_fifo_str" to="specinterface_ln0" fromId="99" toId="15">
</dataflow>
<dataflow id="311" from="StgValue_101" to="specinterface_ln0" fromId="101" toId="15">
</dataflow>
<dataflow id="312" from="StgValue_101" to="specinterface_ln0" fromId="101" toId="15">
</dataflow>
<dataflow id="314" from="p_str411" to="specinterface_ln0" fromId="313" toId="15">
</dataflow>
<dataflow id="315" from="StgValue_101" to="specinterface_ln0" fromId="101" toId="15">
</dataflow>
<dataflow id="316" from="StgValue_101" to="specinterface_ln0" fromId="101" toId="15">
</dataflow>
<dataflow id="318" from="p_str412" to="specinterface_ln0" fromId="317" toId="15">
</dataflow>
<dataflow id="320" from="p_str413" to="specinterface_ln0" fromId="319" toId="15">
</dataflow>
<dataflow id="322" from="p_str414" to="specinterface_ln0" fromId="321" toId="15">
</dataflow>
<dataflow id="323" from="StgValue_114" to="specinterface_ln0" fromId="114" toId="15">
</dataflow>
<dataflow id="324" from="StgValue_114" to="specinterface_ln0" fromId="114" toId="15">
</dataflow>
<dataflow id="325" from="StgValue_117" to="specinterface_ln0" fromId="117" toId="15">
</dataflow>
<dataflow id="326" from="StgValue_117" to="specinterface_ln0" fromId="117" toId="15">
</dataflow>
<dataflow id="328" from="p_str415" to="specinterface_ln0" fromId="327" toId="15">
</dataflow>
<dataflow id="330" from="p_str416" to="specinterface_ln0" fromId="329" toId="15">
</dataflow>
<dataflow id="331" from="_ssdm_op_SpecInterface" to="specinterface_ln0" fromId="96" toId="16">
</dataflow>
<dataflow id="332" from="data_V_data_1_V" to="specinterface_ln0" fromId="49" toId="16">
</dataflow>
<dataflow id="333" from="ap_fifo_str" to="specinterface_ln0" fromId="99" toId="16">
</dataflow>
<dataflow id="334" from="StgValue_101" to="specinterface_ln0" fromId="101" toId="16">
</dataflow>
<dataflow id="335" from="StgValue_101" to="specinterface_ln0" fromId="101" toId="16">
</dataflow>
<dataflow id="337" from="p_str404" to="specinterface_ln0" fromId="336" toId="16">
</dataflow>
<dataflow id="338" from="StgValue_101" to="specinterface_ln0" fromId="101" toId="16">
</dataflow>
<dataflow id="339" from="StgValue_101" to="specinterface_ln0" fromId="101" toId="16">
</dataflow>
<dataflow id="341" from="p_str405" to="specinterface_ln0" fromId="340" toId="16">
</dataflow>
<dataflow id="343" from="p_str406" to="specinterface_ln0" fromId="342" toId="16">
</dataflow>
<dataflow id="345" from="p_str407" to="specinterface_ln0" fromId="344" toId="16">
</dataflow>
<dataflow id="346" from="StgValue_114" to="specinterface_ln0" fromId="114" toId="16">
</dataflow>
<dataflow id="347" from="StgValue_114" to="specinterface_ln0" fromId="114" toId="16">
</dataflow>
<dataflow id="348" from="StgValue_117" to="specinterface_ln0" fromId="117" toId="16">
</dataflow>
<dataflow id="349" from="StgValue_117" to="specinterface_ln0" fromId="117" toId="16">
</dataflow>
<dataflow id="351" from="p_str408" to="specinterface_ln0" fromId="350" toId="16">
</dataflow>
<dataflow id="353" from="p_str409" to="specinterface_ln0" fromId="352" toId="16">
</dataflow>
<dataflow id="354" from="_ssdm_op_SpecInterface" to="specinterface_ln0" fromId="96" toId="17">
</dataflow>
<dataflow id="355" from="data_V_data_0_V" to="specinterface_ln0" fromId="48" toId="17">
</dataflow>
<dataflow id="356" from="ap_fifo_str" to="specinterface_ln0" fromId="99" toId="17">
</dataflow>
<dataflow id="357" from="StgValue_101" to="specinterface_ln0" fromId="101" toId="17">
</dataflow>
<dataflow id="358" from="StgValue_101" to="specinterface_ln0" fromId="101" toId="17">
</dataflow>
<dataflow id="360" from="p_str397" to="specinterface_ln0" fromId="359" toId="17">
</dataflow>
<dataflow id="361" from="StgValue_101" to="specinterface_ln0" fromId="101" toId="17">
</dataflow>
<dataflow id="362" from="StgValue_101" to="specinterface_ln0" fromId="101" toId="17">
</dataflow>
<dataflow id="364" from="p_str398" to="specinterface_ln0" fromId="363" toId="17">
</dataflow>
<dataflow id="366" from="p_str399" to="specinterface_ln0" fromId="365" toId="17">
</dataflow>
<dataflow id="368" from="p_str400" to="specinterface_ln0" fromId="367" toId="17">
</dataflow>
<dataflow id="369" from="StgValue_114" to="specinterface_ln0" fromId="114" toId="17">
</dataflow>
<dataflow id="370" from="StgValue_114" to="specinterface_ln0" fromId="114" toId="17">
</dataflow>
<dataflow id="371" from="StgValue_117" to="specinterface_ln0" fromId="117" toId="17">
</dataflow>
<dataflow id="372" from="StgValue_117" to="specinterface_ln0" fromId="117" toId="17">
</dataflow>
<dataflow id="374" from="p_str401" to="specinterface_ln0" fromId="373" toId="17">
</dataflow>
<dataflow id="376" from="p_str402" to="specinterface_ln0" fromId="375" toId="17">
</dataflow>
<dataflow id="378" from="StgValue_377" to="indvar_flatten" fromId="377" toId="19">
<condition id="-1">
<or_exp><and_exp></and_exp></or_exp>
</condition>
</dataflow>
<dataflow id="379" from="br_ln79" to="indvar_flatten" fromId="18" toId="19">
</dataflow>
<dataflow id="380" from="add_ln79" to="indvar_flatten" fromId="21" toId="19">
<BackEdge/>
<condition id="-1">
<or_exp><and_exp><literal name="icmp_ln79" val="0"/>
</and_exp></or_exp>
</condition>
</dataflow>
<dataflow id="381" from="br_ln0" to="indvar_flatten" fromId="36" toId="19">
<BackEdge/>
</dataflow>
<dataflow id="382" from="indvar_flatten" to="icmp_ln79" fromId="19" toId="20">
</dataflow>
<dataflow id="384" from="StgValue_383" to="icmp_ln79" fromId="383" toId="20">
</dataflow>
<dataflow id="385" from="indvar_flatten" to="add_ln79" fromId="19" toId="21">
</dataflow>
<dataflow id="387" from="StgValue_386" to="add_ln79" fromId="386" toId="21">
</dataflow>
<dataflow id="388" from="icmp_ln79" to="br_ln79" fromId="20" toId="22">
</dataflow>
<dataflow id="390" from="_ssdm_op_Read.ap_fifo.volatile.i16P.i16P.i16P.i16P" to="empty_95" fromId="389" toId="23">
</dataflow>
<dataflow id="391" from="data_V_data_0_V" to="empty_95" fromId="48" toId="23">
</dataflow>
<dataflow id="392" from="data_V_data_1_V" to="empty_95" fromId="49" toId="23">
</dataflow>
<dataflow id="393" from="data_V_data_2_V" to="empty_95" fromId="50" toId="23">
</dataflow>
<dataflow id="394" from="data_V_data_3_V" to="empty_95" fromId="51" toId="23">
</dataflow>
<dataflow id="395" from="empty_95" to="tmp_data_0_V" fromId="23" toId="24">
</dataflow>
<dataflow id="396" from="empty_95" to="tmp_data_1_V" fromId="23" toId="25">
</dataflow>
<dataflow id="397" from="empty_95" to="tmp_data_2_V" fromId="23" toId="26">
</dataflow>
<dataflow id="398" from="empty_95" to="tmp_data_3_V" fromId="23" toId="27">
</dataflow>
<dataflow id="400" from="compute_output_buffer_2d<array,array<ap_fixed<16,6,5,3,0>,8u>,config5>" to="call_ln87" fromId="399" toId="28">
</dataflow>
<dataflow id="401" from="tmp_data_0_V" to="call_ln87" fromId="24" toId="28">
</dataflow>
<dataflow id="402" from="tmp_data_1_V" to="call_ln87" fromId="25" toId="28">
</dataflow>
<dataflow id="403" from="tmp_data_2_V" to="call_ln87" fromId="26" toId="28">
</dataflow>
<dataflow id="404" from="tmp_data_3_V" to="call_ln87" fromId="27" toId="28">
</dataflow>
<dataflow id="405" from="res_V_data_0_V" to="call_ln87" fromId="52" toId="28">
</dataflow>
<dataflow id="406" from="res_V_data_1_V" to="call_ln87" fromId="53" toId="28">
</dataflow>
<dataflow id="407" from="res_V_data_2_V" to="call_ln87" fromId="54" toId="28">
</dataflow>
<dataflow id="408" from="res_V_data_3_V" to="call_ln87" fromId="55" toId="28">
</dataflow>
<dataflow id="409" from="res_V_data_4_V" to="call_ln87" fromId="56" toId="28">
</dataflow>
<dataflow id="410" from="res_V_data_5_V" to="call_ln87" fromId="57" toId="28">
</dataflow>
<dataflow id="411" from="res_V_data_6_V" to="call_ln87" fromId="58" toId="28">
</dataflow>
<dataflow id="412" from="res_V_data_7_V" to="call_ln87" fromId="59" toId="28">
</dataflow>
<dataflow id="413" from="kernel_data_V_1_4" to="call_ln87" fromId="60" toId="28">
</dataflow>
<dataflow id="414" from="kernel_data_V_1_5" to="call_ln87" fromId="61" toId="28">
</dataflow>
<dataflow id="415" from="kernel_data_V_1_6" to="call_ln87" fromId="62" toId="28">
</dataflow>
<dataflow id="416" from="kernel_data_V_1_7" to="call_ln87" fromId="63" toId="28">
</dataflow>
<dataflow id="417" from="kernel_data_V_1_8" to="call_ln87" fromId="64" toId="28">
</dataflow>
<dataflow id="418" from="kernel_data_V_1_9" to="call_ln87" fromId="65" toId="28">
</dataflow>
<dataflow id="419" from="kernel_data_V_1_10" to="call_ln87" fromId="66" toId="28">
</dataflow>
<dataflow id="420" from="kernel_data_V_1_11" to="call_ln87" fromId="67" toId="28">
</dataflow>
<dataflow id="421" from="kernel_data_V_1_16" to="call_ln87" fromId="68" toId="28">
</dataflow>
<dataflow id="422" from="kernel_data_V_1_17" to="call_ln87" fromId="69" toId="28">
</dataflow>
<dataflow id="423" from="kernel_data_V_1_18" to="call_ln87" fromId="70" toId="28">
</dataflow>
<dataflow id="424" from="kernel_data_V_1_19" to="call_ln87" fromId="71" toId="28">
</dataflow>
<dataflow id="425" from="kernel_data_V_1_20" to="call_ln87" fromId="72" toId="28">
</dataflow>
<dataflow id="426" from="kernel_data_V_1_21" to="call_ln87" fromId="73" toId="28">
</dataflow>
<dataflow id="427" from="kernel_data_V_1_22" to="call_ln87" fromId="74" toId="28">
</dataflow>
<dataflow id="428" from="kernel_data_V_1_23" to="call_ln87" fromId="75" toId="28">
</dataflow>
<dataflow id="429" from="kernel_data_V_1_28" to="call_ln87" fromId="76" toId="28">
</dataflow>
<dataflow id="430" from="kernel_data_V_1_29" to="call_ln87" fromId="77" toId="28">
</dataflow>
<dataflow id="431" from="kernel_data_V_1_30" to="call_ln87" fromId="78" toId="28">
</dataflow>
<dataflow id="432" from="kernel_data_V_1_31" to="call_ln87" fromId="79" toId="28">
</dataflow>
<dataflow id="433" from="kernel_data_V_1_32" to="call_ln87" fromId="80" toId="28">
</dataflow>
<dataflow id="434" from="kernel_data_V_1_33" to="call_ln87" fromId="81" toId="28">
</dataflow>
<dataflow id="435" from="kernel_data_V_1_34" to="call_ln87" fromId="82" toId="28">
</dataflow>
<dataflow id="436" from="kernel_data_V_1_35" to="call_ln87" fromId="83" toId="28">
</dataflow>
<dataflow id="437" from="line_buffer_Array_V_1_0_0" to="call_ln87" fromId="84" toId="28">
</dataflow>
<dataflow id="438" from="line_buffer_Array_V_1_1_0" to="call_ln87" fromId="85" toId="28">
</dataflow>
<dataflow id="439" from="line_buffer_Array_V_1_0_1" to="call_ln87" fromId="86" toId="28">
</dataflow>
<dataflow id="440" from="line_buffer_Array_V_1_1_1" to="call_ln87" fromId="87" toId="28">
</dataflow>
<dataflow id="441" from="line_buffer_Array_V_1_0_2" to="call_ln87" fromId="88" toId="28">
</dataflow>
<dataflow id="442" from="line_buffer_Array_V_1_1_2" to="call_ln87" fromId="89" toId="28">
</dataflow>
<dataflow id="443" from="line_buffer_Array_V_1_0_3" to="call_ln87" fromId="90" toId="28">
</dataflow>
<dataflow id="444" from="line_buffer_Array_V_1_1_3" to="call_ln87" fromId="91" toId="28">
</dataflow>
<dataflow id="445" from="sX_2" to="call_ln87" fromId="92" toId="28">
</dataflow>
<dataflow id="446" from="sY_2" to="call_ln87" fromId="93" toId="28">
</dataflow>
<dataflow id="447" from="pY_2" to="call_ln87" fromId="94" toId="28">
</dataflow>
<dataflow id="448" from="pX_2" to="call_ln87" fromId="95" toId="28">
</dataflow>
<dataflow id="450" from="_ssdm_op_SpecLoopName" to="specloopname_ln0" fromId="449" toId="29">
</dataflow>
<dataflow id="452" from="ReadInputHeight_ReadInputWidth_str" to="specloopname_ln0" fromId="451" toId="29">
</dataflow>
<dataflow id="454" from="_ssdm_op_SpecLoopTripCount" to="empty" fromId="453" toId="30">
</dataflow>
<dataflow id="456" from="StgValue_455" to="empty" fromId="455" toId="30">
</dataflow>
<dataflow id="457" from="StgValue_455" to="empty" fromId="455" toId="30">
</dataflow>
<dataflow id="458" from="StgValue_455" to="empty" fromId="455" toId="30">
</dataflow>
<dataflow id="459" from="_ssdm_op_SpecLoopName" to="specloopname_ln81" fromId="449" toId="31">
</dataflow>
<dataflow id="461" from="p_str38" to="specloopname_ln81" fromId="460" toId="31">
</dataflow>
<dataflow id="463" from="_ssdm_op_SpecRegionBegin" to="tmp_s" fromId="462" toId="32">
</dataflow>
<dataflow id="465" from="p_str51" to="tmp_s" fromId="464" toId="32">
</dataflow>
<dataflow id="467" from="_ssdm_op_SpecPipeline" to="specpipeline_ln84" fromId="466" toId="33">
</dataflow>
<dataflow id="469" from="StgValue_468" to="specpipeline_ln84" fromId="468" toId="33">
</dataflow>
<dataflow id="470" from="StgValue_468" to="specpipeline_ln84" fromId="468" toId="33">
</dataflow>
<dataflow id="471" from="StgValue_468" to="specpipeline_ln84" fromId="468" toId="33">
</dataflow>
<dataflow id="472" from="StgValue_101" to="specpipeline_ln84" fromId="101" toId="33">
</dataflow>
<dataflow id="474" from="p_str10" to="specpipeline_ln84" fromId="473" toId="33">
</dataflow>
<dataflow id="476" from="_ssdm_op_SpecRegionEnd" to="empty_94" fromId="475" toId="34">
</dataflow>
<dataflow id="477" from="p_str51" to="empty_94" fromId="464" toId="34">
</dataflow>
<dataflow id="478" from="tmp_s" to="empty_94" fromId="32" toId="34">
</dataflow>
<dataflow id="479" from="compute_output_buffer_2d<array,array<ap_fixed<16,6,5,3,0>,8u>,config5>" to="call_ln87" fromId="399" toId="35">
</dataflow>
<dataflow id="480" from="tmp_data_0_V" to="call_ln87" fromId="24" toId="35">
</dataflow>
<dataflow id="481" from="tmp_data_1_V" to="call_ln87" fromId="25" toId="35">
</dataflow>
<dataflow id="482" from="tmp_data_2_V" to="call_ln87" fromId="26" toId="35">
</dataflow>
<dataflow id="483" from="tmp_data_3_V" to="call_ln87" fromId="27" toId="35">
</dataflow>
<dataflow id="484" from="res_V_data_0_V" to="call_ln87" fromId="52" toId="35">
</dataflow>
<dataflow id="485" from="res_V_data_1_V" to="call_ln87" fromId="53" toId="35">
</dataflow>
<dataflow id="486" from="res_V_data_2_V" to="call_ln87" fromId="54" toId="35">
</dataflow>
<dataflow id="487" from="res_V_data_3_V" to="call_ln87" fromId="55" toId="35">
</dataflow>
<dataflow id="488" from="res_V_data_4_V" to="call_ln87" fromId="56" toId="35">
</dataflow>
<dataflow id="489" from="res_V_data_5_V" to="call_ln87" fromId="57" toId="35">
</dataflow>
<dataflow id="490" from="res_V_data_6_V" to="call_ln87" fromId="58" toId="35">
</dataflow>
<dataflow id="491" from="res_V_data_7_V" to="call_ln87" fromId="59" toId="35">
</dataflow>
<dataflow id="492" from="kernel_data_V_1_4" to="call_ln87" fromId="60" toId="35">
</dataflow>
<dataflow id="493" from="kernel_data_V_1_5" to="call_ln87" fromId="61" toId="35">
</dataflow>
<dataflow id="494" from="kernel_data_V_1_6" to="call_ln87" fromId="62" toId="35">
</dataflow>
<dataflow id="495" from="kernel_data_V_1_7" to="call_ln87" fromId="63" toId="35">
</dataflow>
<dataflow id="496" from="kernel_data_V_1_8" to="call_ln87" fromId="64" toId="35">
</dataflow>
<dataflow id="497" from="kernel_data_V_1_9" to="call_ln87" fromId="65" toId="35">
</dataflow>
<dataflow id="498" from="kernel_data_V_1_10" to="call_ln87" fromId="66" toId="35">
</dataflow>
<dataflow id="499" from="kernel_data_V_1_11" to="call_ln87" fromId="67" toId="35">
</dataflow>
<dataflow id="500" from="kernel_data_V_1_16" to="call_ln87" fromId="68" toId="35">
</dataflow>
<dataflow id="501" from="kernel_data_V_1_17" to="call_ln87" fromId="69" toId="35">
</dataflow>
<dataflow id="502" from="kernel_data_V_1_18" to="call_ln87" fromId="70" toId="35">
</dataflow>
<dataflow id="503" from="kernel_data_V_1_19" to="call_ln87" fromId="71" toId="35">
</dataflow>
<dataflow id="504" from="kernel_data_V_1_20" to="call_ln87" fromId="72" toId="35">
</dataflow>
<dataflow id="505" from="kernel_data_V_1_21" to="call_ln87" fromId="73" toId="35">
</dataflow>
<dataflow id="506" from="kernel_data_V_1_22" to="call_ln87" fromId="74" toId="35">
</dataflow>
<dataflow id="507" from="kernel_data_V_1_23" to="call_ln87" fromId="75" toId="35">
</dataflow>
<dataflow id="508" from="kernel_data_V_1_28" to="call_ln87" fromId="76" toId="35">
</dataflow>
<dataflow id="509" from="kernel_data_V_1_29" to="call_ln87" fromId="77" toId="35">
</dataflow>
<dataflow id="510" from="kernel_data_V_1_30" to="call_ln87" fromId="78" toId="35">
</dataflow>
<dataflow id="511" from="kernel_data_V_1_31" to="call_ln87" fromId="79" toId="35">
</dataflow>
<dataflow id="512" from="kernel_data_V_1_32" to="call_ln87" fromId="80" toId="35">
</dataflow>
<dataflow id="513" from="kernel_data_V_1_33" to="call_ln87" fromId="81" toId="35">
</dataflow>
<dataflow id="514" from="kernel_data_V_1_34" to="call_ln87" fromId="82" toId="35">
</dataflow>
<dataflow id="515" from="kernel_data_V_1_35" to="call_ln87" fromId="83" toId="35">
</dataflow>
<dataflow id="516" from="line_buffer_Array_V_1_0_0" to="call_ln87" fromId="84" toId="35">
</dataflow>
<dataflow id="517" from="line_buffer_Array_V_1_1_0" to="call_ln87" fromId="85" toId="35">
</dataflow>
<dataflow id="518" from="line_buffer_Array_V_1_0_1" to="call_ln87" fromId="86" toId="35">
</dataflow>
<dataflow id="519" from="line_buffer_Array_V_1_1_1" to="call_ln87" fromId="87" toId="35">
</dataflow>
<dataflow id="520" from="line_buffer_Array_V_1_0_2" to="call_ln87" fromId="88" toId="35">
</dataflow>
<dataflow id="521" from="line_buffer_Array_V_1_1_2" to="call_ln87" fromId="89" toId="35">
</dataflow>
<dataflow id="522" from="line_buffer_Array_V_1_0_3" to="call_ln87" fromId="90" toId="35">
</dataflow>
<dataflow id="523" from="line_buffer_Array_V_1_1_3" to="call_ln87" fromId="91" toId="35">
</dataflow>
<dataflow id="524" from="sX_2" to="call_ln87" fromId="92" toId="35">
</dataflow>
<dataflow id="525" from="sY_2" to="call_ln87" fromId="93" toId="35">
</dataflow>
<dataflow id="526" from="pY_2" to="call_ln87" fromId="94" toId="35">
</dataflow>
<dataflow id="527" from="pX_2" to="call_ln87" fromId="95" toId="35">
</dataflow>
<dataflow id="528" from="icmp_ln79" to="StgValue_3" fromId="20" toId="3">
</dataflow>
<dataflow id="529" from="icmp_ln79" to="StgValue_4" fromId="20" toId="4">
</dataflow>
<dataflow id="530" from="icmp_ln79" to="StgValue_2" fromId="20" toId="2">
</dataflow>
</dataflows>


</stg>
